LICENSE
README.md
setup.py
wifuzz/ADB.py
wifuzz/ADBFuzzer.py
wifuzz/BT.py
wifuzz/Config.py
wifuzz/Fuzzer.py
wifuzz/Scanner.py
wifuzz/Utils.py
wifuzz/WiFi.py
wifuzz/__init__.py
wifuzz/__main__.py
wifuzz.egg-info/PKG-INFO
wifuzz.egg-info/SOURCES.txt
wifuzz.egg-info/dependency_links.txt
wifuzz.egg-info/entry_points.txt
wifuzz.egg-info/requires.txt
wifuzz.egg-info/top_level.txt