Metadata-Version: 2.1
Name: wifuzz
Version: 0.1
Summary: wireless fuzzer
Home-page: https://github.com/nbdy/wifuzz
Author: Pascal Eberlein
Author-email: pascal@eberlein.io
License: UNKNOWN
Keywords: fuzzing
Platform: UNKNOWN
Classifier: Intended Audience :: Developers
Classifier: Topic :: Software Development :: Build Tools
Classifier: License :: OSI Approved :: MIT License
Classifier: Programming Language :: Python :: 3
License-File: LICENSE
